coggle/__init__.py
coggle/dataset.py
coggle/ensemble.py
coggle/metrics.py
coggle/utils.py
coggle/image/__init__.py
coggle/image/similarity.py
coggle/image/statistics.py
coggle/llm/__init__.py
coggle/llm/llm_client.py
coggle/parser/__init__.py
coggle/parser/db_parser.py
coggle/parser/doc_parser.py
coggle/parser/html_parser.py
coggle/parser/pdf_parser.py
coggle/parser/ppt_parser.py
coggle/text/__init__.py
coggle/text/similarity.py
coggle/text/statistics.py
coggle/text/retrieval/__init__.py
coggle/text/retrieval/bm25.py
coggle/text/retrieval/embedding.py
coggle/text/retrieval/inverted_index.py
coggle/text/retrieval/tfidf.py
coggle/text/segment/__init__.py
coggle/text/segment/character_segment.py
coggle/text/segment/code_segment.py
coggle/text/segment/markdown_segment.py
coggle/text/segment/sentence_segment.py
coggle/text/segment/word_segment.py
coggle/text/tokenizer/__init__.py
coggle/text/tokenizer/hugingface_tokenizer.py
coggle/text/tokenizer/jieba_tokenizer.py
coggle/text/tokenizer/nltk_tokenizer.py
coggle/text/tokenizer/spacy_tokenizer.py
coggle-0.1.20240114.dist-info/LICENSE
coggle-0.1.20240114.dist-info/METADATA
coggle-0.1.20240114.dist-info/WHEEL
coggle-0.1.20240114.dist-info/top_level.txt
coggle-0.1.20240114.dist-info/RECORD
